Workbook

Sheet Summary
A1: DoorDash × Instacart | Hypothetical Acquisition Model
A2: M&A Case Study | Transaction Valuation, Synergies & Sensitivity
A4: Base Case Transaction
A5: Offer Premium | B5: Offer Equity Value ($mm) | C5: Transaction EV ($mm) | D5: Standalone EV / EBITDA | E5: EBITDA Synergies ($mm) | F5: Synergy-Adj. EBITDA ($mm) | G5: Synergy-Adj. EV / EBITDA | H5: Offer Price / Share
A6: =Assumptions!C12 -> 0.25 | B6: =Model!B6 -> 12851.144 | C6: =Model!B9 -> 12280.144 | D6: =Model!B11 -> 11.29728 | E6: =Model!B21 -> 320 | F6: =Model!B38 -> 1407 | G6: =Model!B39 -> 8.7278918 | H6: =Assumptions!C5*(1+Assumptions!C12) -> 55.5125
A8: Recommendation
A9: PURSUE WITH PRICE DISCIPLINE
A10: Target premium | B10: ~25% | C10: Indicative walk-away | D10: ~30% | E10: Base EBITDA synergies | F10: $320mm | G10: Largest deal risk | H10: Antitrust
A12: Company Snapshot ($mm)
A13: Metric | B13: DoorDash | C13: Instacart | D13: Combined
A14: Revenue | B14: 13717 | C14: 3740 | D14: =SUM(B14:C14) -> 17457
A15: Adjusted EBITDA | B15: 2779 | C15: 1087 | D15: =SUM(B15:C15) -> 3866
A16: Net Income | B16: 935 | C16: 447 | D16: =SUM(B16:C16) -> 1382
A17: Commerce Volume | B17: 102020 | C17: 37220 | D17: =SUM(B17:C17) -> 139240 | J17: Metric | K17: $mm
J18: Standalone EBITDA | K18: 1087
A19: Model Note | J19: Synergy-Adjusted EBITDA | K19: =Model!B38 -> 1407
A20: Illustrative portfolio model. Acquisition premium, financing mix, synergies and integration costs are hypothetical and do not represent company guidance.

Sheet Assumptions
A1: DoorDash × Instacart Acquisition Model
A3: Key Inputs ($mm except per-share data)
A4: Input | B4: DoorDash | C4: Instacart / Value | D4: Units | E4: Date | F4: Source
A5: Share price | B5: 193.73 | C5: 44.41 | D5: $/share | E5: 2026-09-22 | F5: StockAnalysis
A6: Diluted shares | B6: 433.3 | C6: 231.5 | D6: mm | E6: 2026-09-22 / 2026-07-31 | F6: StockAnalysis / SEC
A7: Revenue | B7: 13717 | C7: 3740 | D7: $mm | E7: FY2025 | F7: SEC 10-K
A8: Adjusted EBITDA | B8: 2779 | C8: 1087 | D8: $mm | E8: FY2025 | F8: SEC 10-K
A9: Net income | B9: 935 | C9: 447 | D9: $mm | E9: FY2025 | F9: SEC 10-K
A10: Cash + securities | B10: 6300 | C10: 767 | D10: $mm | E10: 2025-12-31 | F10: SEC 10-K
A11: Preferred stock | B11: 0 | C11: 196 | D11: $mm | E11: 2025-12-31 | F11: SEC 10-K
A12: Acquisition premium | C12: 0.25 | D12: % | E12: Model | F12: Illustrative
A13: Cash consideration % | C13: 0.3 | D13: % | E13: Model | F13: Illustrative
A14: Debt consideration % | C14: 0.3 | D14: % | E14: Model | F14: Illustrative
A15: Stock consideration % | C15: 0.4 | D15: % | E15: Model | F15: Illustrative
A16: New debt interest rate | C16: 0.055 | D16: % | E16: Model | F16: Illustrative
A17: Tax rate | C17: 0.25 | D17: % | E17: Model | F17: Illustrative
A18: Cost synergies | C18: 250 | D18: $mm | E18: Model | F18: Illustrative
A19: Revenue synergies | C19: 200 | D19: $mm | E19: Model | F19: Illustrative
A20: EBITDA margin on revenue synergies | C20: 0.35 | D20: % | E20: Model | F20: Illustrative
A21: One-time integration costs | C21: 500 | D21: $mm | E21: Model | F21: Illustrative
A22: Valuation Discipline
A23: Indicative walk-away premium | C23: 0.3 | D23: % | E23: Model | F23: Illustrative

Sheet Model
A1: Transaction Model
A3: Purchase Price
A4: Metric | B4: Value | C4: Units
A5: Current Instacart equity value | B5: =Assumptions!C5*Assumptions!C6 -> 10280.915 | C5: $mm
A6: Offer equity value | B6: =B5*(1+Assumptions!C12) -> 12851.144 | C6: $mm
A7: Target cash + securities | B7: =Assumptions!C10 -> 767 | C7: $mm
A8: Target preferred stock | B8: =Assumptions!C11 -> 196 | C8: $mm
A9: Transaction enterprise value | B9: =B6+B8-B7 -> 12280.144 | C9: $mm
A10: EV / Revenue | B10: =B9/Assumptions!C7 -> 3.2834609 | C10: x
A11: EV / Adj. EBITDA | B11: =B9/Assumptions!C8 -> 11.29728 | C11: x
A13: Financing & Synergies
A14: Metric | B14: Value | C14: Units
A15: Cash funded | B15: =B6*Assumptions!C13 -> 3855.3431 | C15: $mm
A16: New debt | B16: =B6*Assumptions!C14 -> 3855.3431 | C16: $mm
A17: Stock consideration | B17: =B6*Assumptions!C15 -> 5140.4575 | C17: $mm
A18: New DASH shares | B18: =B17/Assumptions!B5 -> 26.534133 | C18: mm
A19: Annual interest expense | B19: =B16*Assumptions!C16 -> 212.04387 | C19: $mm
A20: EBITDA from revenue synergies | B20: =Assumptions!C19*Assumptions!C20 -> 70 | C20: $mm
A21: Total EBITDA synergies | B21: =Assumptions!C18+B20 -> 320 | C21: $mm
A22: Pro forma revenue | B22: =Assumptions!B7+Assumptions!C7+Assumptions!C19 -> 17657 | C22: $mm
A23: Pro forma EBITDA | B23: =Assumptions!B8+Assumptions!C8+B21 -> 4186 | C23: $mm
A24: Pro forma EBITDA margin | B24: =B23/B22 -> 0.23707312 | C24: %
A26: Illustrative EPS Accretion / Dilution
A27: Metric | B27: Value | C27: Units
A28: DoorDash standalone EPS | B28: =Assumptions!B9/Assumptions!B6 -> 2.1578583 | C28: $/share
A29: After-tax synergies | B29: =B21*(1-Assumptions!C17) -> 240 | C29: $mm
A30: After-tax interest | B30: =B19*(1-Assumptions!C17) -> 159.0329 | C30: $mm
A31: Pro forma net income | B31: =Assumptions!B9+Assumptions!C9+B29-B30 -> 1462.9671 | C31: $mm
A32: Pro forma shares | B32: =Assumptions!B6+B18 -> 459.83413 | C32: mm
A33: Pro forma EPS | B33: =B31/B32 -> 3.1815104 | C33: $/share
A34: EPS accretion / (dilution) | B34: =B33/B28-1 -> 0.4743834 | C34: %
A36: Synergy-Adjusted Valuation
A37: Metric | B37: Value | C37: Units
A38: Synergy-adjusted EBITDA | B38: =Assumptions!C8+B21 -> 1407 | C38: $mm
A39: EV / Synergy-adjusted EBITDA | B39: =B9/B38 -> 8.7278918 | C39: x

Sheet Sensitivity
A1: Synergy-Adjusted EV / EBITDA Sensitivity
A3: EBITDA Synergies \ Acquisition Premium | B3: 0.15 | C3: 0.2 | D3: 0.25 | E3: 0.3 | F3: 0.35
A4: 150 | B4: =(Model!$B$5*(1+B$3)+Assumptions!$C$11-Assumptions!$C$10)/(Assumptions!$C$8+$A4) -> 9.0962427 | C4: =(Model!$B$5*(1+C$3)+Assumptions!$C$11-Assumptions!$C$10)/(Assumptions!$C$8+$A4) -> 9.5118011 | D4: =(Model!$B$5*(1+D$3)+Assumptions!$C$11-Assumptions!$C$10)/(Assumptions!$C$8+$A4) -> 9.9273595 | E4: =(Model!$B$5*(1+E$3)+Assumptions!$C$11-Assumptions!$C$10)/(Assumptions!$C$8+$A4) -> 10.342918 | F4: =(Model!$B$5*(1+F$3)+Assumptions!$C$11-Assumptions!$C$10)/(Assumptions!$C$8+$A4) -> 10.758476
A5: 250 | B5: =(Model!$B$5*(1+B$3)+Assumptions!$C$11-Assumptions!$C$10)/(Assumptions!$C$8+$A5) -> 8.4158955 | C5: =(Model!$B$5*(1+C$3)+Assumptions!$C$11-Assumptions!$C$10)/(Assumptions!$C$8+$A5) -> 8.8003725 | D5: =(Model!$B$5*(1+D$3)+Assumptions!$C$11-Assumptions!$C$10)/(Assumptions!$C$8+$A5) -> 9.1848495 | E5: =(Model!$B$5*(1+E$3)+Assumptions!$C$11-Assumptions!$C$10)/(Assumptions!$C$8+$A5) -> 9.5693265 | F5: =(Model!$B$5*(1+F$3)+Assumptions!$C$11-Assumptions!$C$10)/(Assumptions!$C$8+$A5) -> 9.9538035
A6: 320 | B6: =(Model!$B$5*(1+B$3)+Assumptions!$C$11-Assumptions!$C$10)/(Assumptions!$C$8+$A6) -> 7.9971942 | C6: =(Model!$B$5*(1+C$3)+Assumptions!$C$11-Assumptions!$C$10)/(Assumptions!$C$8+$A6) -> 8.362543 | D6: =(Model!$B$5*(1+D$3)+Assumptions!$C$11-Assumptions!$C$10)/(Assumptions!$C$8+$A6) -> 8.7278918 | E6: =(Model!$B$5*(1+E$3)+Assumptions!$C$11-Assumptions!$C$10)/(Assumptions!$C$8+$A6) -> 9.0932406 | F6: =(Model!$B$5*(1+F$3)+Assumptions!$C$11-Assumptions!$C$10)/(Assumptions!$C$8+$A6) -> 9.4585894
A7: 400 | B7: =(Model!$B$5*(1+B$3)+Assumptions!$C$11-Assumptions!$C$10)/(Assumptions!$C$8+$A7) -> 7.5669484 | C7: =(Model!$B$5*(1+C$3)+Assumptions!$C$11-Assumptions!$C$10)/(Assumptions!$C$8+$A7) -> 7.9126416 | D7: =(Model!$B$5*(1+D$3)+Assumptions!$C$11-Assumptions!$C$10)/(Assumptions!$C$8+$A7) -> 8.2583347 | E7: =(Model!$B$5*(1+E$3)+Assumptions!$C$11-Assumptions!$C$10)/(Assumptions!$C$8+$A7) -> 8.6040279 | F7: =(Model!$B$5*(1+F$3)+Assumptions!$C$11-Assumptions!$C$10)/(Assumptions!$C$8+$A7) -> 8.9497211
A8: 550 | B8: =(Model!$B$5*(1+B$3)+Assumptions!$C$11-Assumptions!$C$10)/(Assumptions!$C$8+$A8) -> 6.8735811 | C8: =(Model!$B$5*(1+C$3)+Assumptions!$C$11-Assumptions!$C$10)/(Assumptions!$C$8+$A8) -> 7.187598 | D8: =(Model!$B$5*(1+D$3)+Assumptions!$C$11-Assumptions!$C$10)/(Assumptions!$C$8+$A8) -> 7.501615 | E8: =(Model!$B$5*(1+E$3)+Assumptions!$C$11-Assumptions!$C$10)/(Assumptions!$C$8+$A8) -> 7.8156319 | F8: =(Model!$B$5*(1+F$3)+Assumptions!$C$11-Assumptions!$C$10)/(Assumptions!$C$8+$A8) -> 8.1296489

Sheet Sources
A1: Sources
A3: Item | B3: Source | C3: URL
A4: Instacart reference market price / shares | B4: StockAnalysis | C4: https://stockanalysis.com/stocks/cart/
A5: Instacart 2025 financials | B5: SEC 10-K | C5: https://www.sec.gov/Archives/edgar/data/1579091/000157909126000018/cart-20251231.htm
A6: Instacart Q2 2026 shares | B6: SEC 10-Q | C6: https://www.sec.gov/Archives/edgar/data/1579091/000157909126000042/cart-20260630.htm
A7: DoorDash 2025 financials | B7: SEC 10-K | C7: https://www.sec.gov/Archives/edgar/data/1792789/000179278926000013/dash-20251231.htm
A8: DoorDash market price / shares | B8: StockAnalysis | C8: https://stockanalysis.com/stocks/dash/
A9: DoorDash Q2 2026 results | B9: DoorDash IR | C9: https://ir.doordash.com/financials/quarterly-results/
A10: Model assumptions | B10: Illustrative | C10: User-adjustable assumptions in Assumptions sheet
A11: DoorDash Deliveroo acquisition | B11: DoorDash IR | C11: https://ir.doordash.com/news/news-details/2025/DoorDash-Announces-Agreement-to-Acquire-Deliveroo/default.aspx
A12: Illustrative case assumptions | B12: Portfolio case study | C12: Acquisition premium, financing mix, synergies and integration costs are hypothetical.

Sheet Scenarios
A1: Scenario Analysis
A3: Metric | B3: Bear | C3: Base | D3: Bull | E3: Units | F3: Notes
A4: Acquisition premium | B4: 0.15 | C4: 0.25 | D4: 0.35 | E4: % | F4: Illustrative
A5: Cost synergies | B5: 150 | C5: 250 | D5: 400 | E5: $mm | F5: Illustrative
A6: Revenue synergies | B6: 100 | C6: 200 | D6: 350 | E6: $mm | F6: Illustrative
A7: Revenue synergy EBITDA margin | B7: 0.35 | C7: 0.35 | D7: 0.35 | E7: % | F7: Illustrative
A8: Total EBITDA synergies | B8: =B5+(B6*B7) -> 185 | C8: =C5+(C6*C7) -> 320 | D8: =D5+(D6*D7) -> 522.5 | E8: $mm | F8: Cost + revenue synergy EBITDA
A9: Offer equity value | B9: =Model!$B$5*(1+B4) -> 11823.052 | C9: =Model!$B$5*(1+C4) -> 12851.144 | D9: =Model!$B$5*(1+D4) -> 13879.235 | E9: $mm | F9: Reference equity value × (1 + premium)
A10: Transaction EV | B10: =B9+Assumptions!$C$11-Assumptions!$C$10 -> 11252.052 | C10: =C9+Assumptions!$C$11-Assumptions!$C$10 -> 12280.144 | D10: =D9+Assumptions!$C$11-Assumptions!$C$10 -> 13308.235 | E10: $mm | F10: Offer equity value + preferred - cash
A11: EV / Standalone EBITDA | B11: =B10/Assumptions!$C$8 -> 10.351474 | C11: =C10/Assumptions!$C$8 -> 11.29728 | D11: =D10/Assumptions!$C$8 -> 12.243087 | E11: x | F11: Transaction EV / Instacart EBITDA
A12: EV / Synergy-adjusted EBITDA | B12: =B10/(Assumptions!$C$8+B8) -> 8.845953 | C12: =C10/(Assumptions!$C$8+C8) -> 8.7278918 | D12: =D10/(Assumptions!$C$8+D8) -> 8.2685525 | E12: x | F12: Transaction EV / (Instacart EBITDA + synergies)
